shopify_webhook/__init__.py
shopify_webhook/decorators.py
shopify_webhook/helpers.py
shopify_webhook/signals.py
shopify_webhook/views.py
shopify_webhook/tests/__init__.py
shopify_webhook/tests/test_app_proxy.py
shopify_webhook/tests/test_webhook.py
shopify_webhook/tests/urls.py
django_shopify_webhook-0.5.1.dist-info/LICENSE
django_shopify_webhook-0.5.1.dist-info/METADATA
django_shopify_webhook-0.5.1.dist-info/WHEEL
django_shopify_webhook-0.5.1.dist-info/top_level.txt
django_shopify_webhook-0.5.1.dist-info/zip-safe
django_shopify_webhook-0.5.1.dist-info/RECORD
