Metadata-Version: 2.1
Name: django-shopify-webhook
Version: 0.5.1
Summary: A package for the creation of Shopify Apps using the Embedded App SDK.
Home-page: https://github.com/discolabs/django-shopify-webhook
Author: Gavin Ballard
Author-email: gavin@discolabs.com
License: None
Platform: UNKNOWN
Requires-Dist: django (>=1.7)
